xmlu/__init__.py
xmlu/convert_to_json.py
xmlu/convert_to_pydantic.py
xmlu/main.py
xmlu/utils.py
xmlu-0.1.2.dist-info/METADATA
xmlu-0.1.2.dist-info/WHEEL
xmlu-0.1.2.dist-info/entry_points.txt
xmlu-0.1.2.dist-info/licenses/LICENSE
xmlu-0.1.2.dist-info/RECORD
