Metadata-Version: 2.4
Name: xmlu
Version: 0.1.2
Summary: XML Utility tools with Pydantic and Typer
Project-URL: Homepage, https://github.com/MichielMe/xmlu
Project-URL: Repository, https://github.com/MichielMe/xmlu.git
Author-email: Michiel Meire <michiel.meire1@gmail.com>
License: MIT
License-File: LICENSE
Keywords: parsing,pydantic,pydantic-converter,typer,validation,xml,xml-utility
Classifier: Development Status :: 4 - Beta
Classifier: Intended Audience :: Developers
Classifier: License :: OSI Approved :: MIT License
Classifier: Operating System :: OS Independent
Classifier: Programming Language :: Python :: 3
Classifier: Programming Language :: Python :: 3.12
Classifier: Topic :: Software Development :: Libraries :: Python Modules
Classifier: Topic :: Text Processing :: Markup :: XML
Requires-Python: >=3.12
Requires-Dist: lxml>=6.0.2
Requires-Dist: pydantic>=2.12.3
Requires-Dist: typer>=0.20.0
